zilliz_mcp_server/__init__.py
zilliz_mcp_server/app.py
zilliz_mcp_server/server.py
zilliz_mcp_server/settings.py
zilliz_mcp_server/common/__init__.py
zilliz_mcp_server/common/openapi_client.py
zilliz_mcp_server/tools/__init__.py
zilliz_mcp_server/tools/milvus/__init__.py
zilliz_mcp_server/tools/milvus/milvus_tools.py
zilliz_mcp_server/tools/zilliz/__init__.py
zilliz_mcp_server/tools/zilliz/zilliz_tools.py
zilliz_mcp_server-1.0.0.dist-info/METADATA
zilliz_mcp_server-1.0.0.dist-info/WHEEL
zilliz_mcp_server-1.0.0.dist-info/entry_points.txt
zilliz_mcp_server-1.0.0.dist-info/licenses/LICENSE
zilliz_mcp_server-1.0.0.dist-info/RECORD
