Metadata-Version: 2.4
Name: zilliz-mcp-server
Version: 1.0.0
Summary: MCP server for Zilliz Cloud and Milvus
Author-email: Zilliz <support@zilliz.com>
License: Apache-2.0
License-File: LICENSE
Keywords: ai,embeddings,mcp,milvus,rag,semantic-search,vector-database,zilliz
Classifier: Development Status :: 4 - Beta
Classifier: Environment :: Console
Classifier: Intended Audience :: Developers
Classifier: License :: OSI Approved :: Apache Software License
Classifier: Programming Language :: Python :: 3
Classifier: Programming Language :: Python :: 3.10
Classifier: Programming Language :: Python :: 3.11
Classifier: Programming Language :: Python :: 3.12
Classifier: Topic :: Database
Classifier: Topic :: Internet :: WWW/HTTP :: HTTP Servers
Classifier: Topic :: Scientific/Engineering :: Artificial Intelligence
Classifier: Topic :: Software Development :: Libraries :: Python Modules
Requires-Python: >=3.10
Requires-Dist: fastmcp>=2.6.1
Requires-Dist: python-dotenv>=1.0.0
Requires-Dist: requests>=2.31.0
Provides-Extra: test
Requires-Dist: pytest-asyncio>=1.0.0; extra == 'test'
Requires-Dist: pytest-mock>=3.14.1; extra == 'test'
Requires-Dist: pytest>=8.4.1; extra == 'test'
Requires-Dist: responses>=0.25.7; extra == 'test'
